graiax/playwright/__init__.py
graiax/playwright/i18n.py
graiax/playwright/installer.py
graiax/playwright/locale/zh_CN/LC_MESSAGES/graiax-playwright.mo
graiax/playwright/locale/zh_CN/LC_MESSAGES/graiax-playwright.po
graiax/playwright/py.typed
graiax/playwright/service.py
graiax/playwright/utils.py
graiax_playwright-0.5.0.dist-info/METADATA
graiax_playwright-0.5.0.dist-info/WHEEL
graiax_playwright-0.5.0.dist-info/entry_points.txt
graiax_playwright-0.5.0.dist-info/licenses/LICENSE
graiax_playwright-0.5.0.dist-info/RECORD
