Metadata-Version: 2.1
Name: graiax-playwright
Version: 0.5.0
Summary: 适用于 Graia 的 Playwright 管理器
Keywords: graia,graiax,launart,playwright
Author-Email: BlueGlassBlock <blueglassblock@outlook.com>, I Love Study <1450069615@qq.com>, Redlnn <red_lnn@outlook.com>, RF-Tar-Railt <rf_tar_railt@qq.com>
License: MIT
Classifier: Typing :: Typed
Classifier: Development Status :: 4 - Beta
Classifier: Programming Language :: Python :: 3
Classifier: Programming Language :: Python :: 3.9
Classifier: Programming Language :: Python :: 3.10
Classifier: Programming Language :: Python :: 3.11
Classifier: Programming Language :: Python :: 3.12
Classifier: Programming Language :: Python :: 3.13
Classifier: Programming Language :: Python :: 3.14
Project-URL: repository, https://github.com/GraiaCommunity/graiax-playwright
Requires-Python: >=3.10
Requires-Dist: launart>=0.8.2
Requires-Dist: loguru>=0.7.2
Requires-Dist: playwright>=1.46.0
